emx/__init__.py
emx/__main__.py
emx/http.py
emx-1.1.1.dist-info/METADATA
emx-1.1.1.dist-info/WHEEL
emx-1.1.1.dist-info/entry_points.txt
emx-1.1.1.dist-info/top_level.txt
emx-1.1.1.dist-info/RECORD
